semantic_versioning/__init__.py
semantic_versioning/_version.py
semantic_versioning/flags.py
semantic_versioning/patterns.py
semantic_versioning/semantic_version.py
semantic_versioning/specifier.py
semantic_versioning/utils.py
semantic_versioning-0.1.5.dist-info/LICENSE
semantic_versioning-0.1.5.dist-info/METADATA
semantic_versioning-0.1.5.dist-info/WHEEL
semantic_versioning-0.1.5.dist-info/top_level.txt
semantic_versioning-0.1.5.dist-info/RECORD
