Metadata-Version: 2.1
Name: semantic-versioning
Version: 0.1.5
Summary: A package for easily managing Semantic versions as described in PEP440.
Maintainer-email: Jesse de Ruijter <jessederuijter@gmail.com>
Requires-Python: >=3.10
License-File: LICENSE
Provides-Extra: dev
Requires-Dist: pytest ; extra == 'dev'
Requires-Dist: black ; extra == 'dev'
Requires-Dist: pre-commit ; extra == 'dev'
Requires-Dist: isort ; extra == 'dev'
Requires-Dist: bandit ==1.7.0 ; extra == 'dev'
Requires-Dist: flake8 ; extra == 'dev'
